byted_overpass_webarch_flow_parallel_unrecommend_7b/__init__.py
byted_overpass_webarch_flow_parallel_unrecommend_7b-0.0.1.dist-info/METADATA
byted_overpass_webarch_flow_parallel_unrecommend_7b-0.0.1.dist-info/WHEEL
byted_overpass_webarch_flow_parallel_unrecommend_7b-0.0.1.dist-info/top_level.txt
byted_overpass_webarch_flow_parallel_unrecommend_7b-0.0.1.dist-info/RECORD
