Metadata-Version: 2.1
Name: byted-overpass-webarch-flow-parallel-unrecommend-7b
Version: 0.0.1
Summary: A simple package named byted_overpass_webarch_flow_parallel_unrecommend_7b
Home-page: https://github.com/artifact/byted_overpass_webarch_flow_parallel_unrecommend_7b.git
Author: artifact
Author-email: artifact@example.com
License: UNKNOWN
Platform: UNKNOWN
Classifier: Programming Language :: Python :: 3
Classifier: License :: OSI Approved :: MIT License
Classifier: Operating System :: OS Independent
